app/__init__.py
norris_cli-2.0.dist-info/LICENSE
norris_cli-2.0.dist-info/METADATA
norris_cli-2.0.dist-info/WHEEL
norris_cli-2.0.dist-info/entry_points.txt
norris_cli-2.0.dist-info/top_level.txt
norris_cli-2.0.dist-info/RECORD
