Metadata-Version: 2.1
Name: norris-cli
Version: 2.0
Summary: A simple cli app that brightens up your day with Chuck Norris jokes.
Home-page: https://github.com/wangonya/norris-cli
Author: Kinyanjui Wangonya
Author-email: kwangonya@gmail.com
License: MIT
Platform: UNKNOWN
Classifier: License :: OSI Approved :: MIT License
Classifier: Programming Language :: Python :: 3
Classifier: Programming Language :: Python :: 3.7
Requires-Dist: Click
Requires-Dist: requests
Requires-Dist: halo
